iqmotion/README.md
iqmotion/__init__.py
iqmotion/custom_errors.py
iqmotion/client_entries/__init__.py
iqmotion/client_entries/client_entry.py
iqmotion/client_entries/client_entry_data.py
iqmotion/client_entries/dictionary_client_entry.py
iqmotion/client_entries/process_client_entry.py
iqmotion/clients/__init__.py
iqmotion/clients/client.py
iqmotion/clients/client_with_entries.py
iqmotion/clients/client_files/.git
iqmotion/clients/client_files/.gitignore
iqmotion/clients/client_files/LICENSE
iqmotion/clients/client_files/__init__.py
iqmotion/clients/client_files/adc_interface.json
iqmotion/clients/client_files/anticogging.json
iqmotion/clients/client_files/anticogging_pro.json
iqmotion/clients/client_files/arming_handler.json
iqmotion/clients/client_files/bitbucket-pipelines.yml
iqmotion/clients/client_files/brushless_drive.json
iqmotion/clients/client_files/buzzer_control.json
iqmotion/clients/client_files/coil_temperature_estimator.json
iqmotion/clients/client_files/current_safeties.json
iqmotion/clients/client_files/drive_control_interface.json
iqmotion/clients/client_files/esc_propeller_input_parser.json
iqmotion/clients/client_files/field_weakening_controller.json
iqmotion/clients/client_files/gpio_controller.json
iqmotion/clients/client_files/hobby_input.json
iqmotion/clients/client_files/iquart_flight_controller_interface.json
iqmotion/clients/client_files/mag_alpha.json
iqmotion/clients/client_files/motor_driver.json
iqmotion/clients/client_files/motor_model.json
iqmotion/clients/client_files/multi_turn_angle_control.json
iqmotion/clients/client_files/persistent_memory.json
iqmotion/clients/client_files/power_monitor.json
iqmotion/clients/client_files/power_safety.json
iqmotion/clients/client_files/propeller_motor_control.json
iqmotion/clients/client_files/pulsing_rectangular_input_parser.json
iqmotion/clients/client_files/pwm_interface.json
iqmotion/clients/client_files/rgb_led.json
iqmotion/clients/client_files/rotor_angle_generator.json
iqmotion-0.29.1.dist-info/METADATA
iqmotion-0.29.1.dist-info/WHEEL
iqmotion-0.29.1.dist-info/top_level.txt
iqmotion-0.29.1.dist-info/RECORD
