Metadata-Version: 2.1
Name: iqmotion
Version: 0.29.1
Summary: Python libraries to talk to IQ Motion Control devices
Home-page: https://github.com/iq-motion-control/iq-module-communication-python
Author: Ben Quan, Malik B. Parker, Raphael Van Hoffelen
Author-email: ben.quan@vertiq.co
License: lgpl-3.0
Download-URL: https://github.com/iq-motion-control/iq-module-communication-python/releases
Keywords: IQ,IQ CONTROL,IQ MOTION CONTROL,API,IQ MODULES,IQ LIBRARIES
Platform: UNKNOWN
Classifier: Intended Audience :: Developers
Classifier: Topic :: Software Development :: Libraries
Classifier: License :: OSI Approved :: GNU Lesser General Public License v3 or later (LGPLv3+)
Classifier: Programming Language :: Python :: 3.7
Classifier: Programming Language :: Python :: 3.8
Requires-Python: >=3.7
Requires-Dist: numpy
Requires-Dist: pyserial
